sodiumicu2023/__init__.py
sodiumicu2023/webpage_data.py
sodiumicu2023-1.0.0.2.dist-info/METADATA
sodiumicu2023-1.0.0.2.dist-info/WHEEL
sodiumicu2023-1.0.0.2.dist-info/top_level.txt
sodiumicu2023-1.0.0.2.dist-info/RECORD
